forecastui/__init__.py
forecastui/app.py
forecastui/api/__init__.py
forecastui/api/board.py
forecastui/api/connection.py
forecastui/api/filesystem.py
forecastui/api/presets.py
forecastui/api/settings.py
forecastui/assets/logo.svg
forecastui/callbacks/__init__.py
forecastui/callbacks/callback_manager.py
forecastui/callbacks/parameter_callback.py
forecastui/callbacks/preset_callback.py
forecastui/communication/__init__.py
forecastui/communication/serial_handler.py
forecastui/communication/serial_manager.py
forecastui/dist_client/favicon.ico
forecastui/dist_client/index.html
forecastui/dist_client/static/css/app.bdf8dfe5.css
forecastui/dist_client/static/css/chunk-vendors.b91163a1.css
forecastui/dist_client/static/fonts/Roboto-Black.313a6563.woff
forecastui/dist_client/static/fonts/Roboto-Black.59eb3601.woff2
forecastui/dist_client/static/fonts/Roboto-BlackItalic.cc2fadc3.woff
forecastui/dist_client/static/fonts/Roboto-BlackItalic.f75569f8.woff2
forecastui/dist_client/static/fonts/Roboto-Bold.50d75e48.woff
forecastui/dist_client/static/fonts/Roboto-Bold.b52fac2b.woff2
forecastui/dist_client/static/fonts/Roboto-BoldItalic.4fe0f73c.woff
forecastui/dist_client/static/fonts/Roboto-BoldItalic.94008e69.woff2
forecastui/dist_client/static/fonts/Roboto-Light.c73eb1ce.woff
forecastui/dist_client/static/fonts/Roboto-Light.d26871e8.woff2
forecastui/dist_client/static/fonts/Roboto-LightItalic.13efe6cb.woff
forecastui/dist_client/static/fonts/Roboto-LightItalic.e8eaae90.woff2
forecastui/dist_client/static/fonts/Roboto-Medium.1d659482.woff
forecastui/dist_client/static/fonts/Roboto-Medium.90d16760.woff2
forecastui/dist_client/static/fonts/Roboto-MediumItalic.13ec0eb5.woff2
forecastui/dist_client/static/fonts/Roboto-MediumItalic.83e114c3.woff
forecastui/dist_client/static/fonts/Roboto-Regular.35b07eb2.woff
forecastui/dist_client/static/fonts/Roboto-Regular.73f0a88b.woff2
forecastui/dist_client/static/fonts/Roboto-RegularItalic.4357beb8.woff2
forecastui-0.4.6.dist-info/LICENSE
forecastui-0.4.6.dist-info/METADATA
forecastui-0.4.6.dist-info/WHEEL
forecastui-0.4.6.dist-info/entry_points.txt
forecastui-0.4.6.dist-info/top_level.txt
forecastui-0.4.6.dist-info/RECORD
