Metadata-Version: 2.1
Name: forecastui
Version: 0.4.6
Summary: User interface designed for data logging over serial
Home-page: https://gitlab.com/altairLab/elasticteam/forecast/forecast-atlas
Author: Matteo Meneghetti
Author-email: matteo@meneghetti.dev
Project-URL: Source, https://gitlab.com/altairLab/elasticteam/forecast/forecast-atlas
Classifier: Development Status :: 3 - Alpha
Classifier: Intended Audience :: Developers
Classifier: License :: OSI Approved :: MIT License
Classifier: Programming Language :: Python :: 3
Requires-Python: >=3.5
License-File: LICENSE
Requires-Dist: flask
Requires-Dist: flask-restful
Requires-Dist: flask-socketio (>=5.0)
Requires-Dist: requests
Requires-Dist: pyyaml (>=5.0)
Requires-Dist: easyserial (>=0.2)
Provides-Extra: qt
Requires-Dist: pycuteweb ; extra == 'qt'
